<beans:beans xmlns="http://www.springframework.org/schema/security"
             xmlns:beans="http://www.springframework.org/schema/beans"
             xmlns:xsi="http://www.w3.org/2001/XMLSchema-instance"
             xsi:schemaLocation="http://www.springframework.org/schema/beans
            http://www.springframework.org/schema/beans/spring-beans.xsd
            http://www.springframework.org/schema/security
            http://www.springframework.org/schema/security/spring-security.xsd">

    <http auto-config="true" >
        <intercept-url pattern="/" access="permitAll" />
        <intercept-url pattern="/admin/**" access="hasRole('ADMIN')" />
        <intercept-url pattern="/computerDmo/**" access="hasRole('USER')" />
        <form-login  login-page="/login"
                     username-parameter="username"
                     password-parameter="password"
                     authentication-failure-url="/denied" />
        <csrf/>
    </http>

    <authentication-manager >
        <authentication-provider userDmo-service-ref="customUserDetailsService"/>
    </authentication-manager>

    <beans:bean id="customUserDetailsService" class="com.louisamoros.cdb.security.CustomUserDetailsService" />

</beans:beans>